agrolens
