Metadata-Version: 2.1
Name: agrolens
Version: 1.0.1
Summary: Some description
Author: myname
License: MIT
